{
    "11":  {
               "timestamp":  "2026-03-15T20:54:59Z",
               "event":  "Scan",
               "ScanType":  "Detailed",
               "BodyName":  "Fachia BP-A d13 AB 5",
               "BodyID":  11,
               "Parents":  [
                               "@{Null=9}",
                               "@{Null=1}",
                               "@{Null=0}"
                           ],
               "StarSystem":  "Fachia BP-A d13",
               "SystemAddress":  459955559171,
               "DistanceFromArrivalLS":  3018.911495,
               "TidalLock":  false,
               "TerraformState":  "",
               "PlanetClass":  "High metal content body",
               "Atmosphere":  "",
               "AtmosphereType":  "None",
               "Volcanism":  "",
               "MassEM":  0.366638,
               "Radius":  4480855.000000,
               "SurfaceGravity":  7.278210,
               "SurfaceTemperature":  569.135803,
               "SurfacePressure":  0.000000,
               "Landable":  true,
               "Materials":  [
                                 "@{Name=iron; Percent=23.413549}",
                                 "@{Name=nickel; Percent=17.709026}",
                                 "@{Name=sulphur; Percent=16.618643}",
                                 "@{Name=carbon; Percent=13.974556}",
                                 "@{Name=chromium; Percent=10.529851}",
                                 "@{Name=phosphorus; Percent=8.946752}",
                                 "@{Name=selenium; Percent=2.600958}",
                                 "@{Name=arsenic; Percent=2.185579}",
                                 "@{Name=niobium; Percent=1.600191}",
                                 "@{Name=yttrium; Percent=1.398463}",
                                 "@{Name=mercury; Percent=1.022431}"
                             ],
               "Composition":  {
                                   "Ice":  0.000000,
                                   "Rock":  0.669877,
                                   "Metal":  0.330123
                               },
               "SemiMajorAxis":  1091040253.639221,
               "Eccentricity":  0.078017,
               "OrbitalInclination":  3.125115,
               "Periapsis":  277.486199,
               "OrbitalPeriod":  26091095.805168,
               "AscendingNode":  -168.747022,
               "MeanAnomaly":  111.991412,
               "RotationPeriod":  168948.453646,
               "AxialTilt":  -0.475646,
               "WasDiscovered":  false,
               "WasMapped":  false,
               "WasFootfalled":  false
           },
    "3":  {
              "timestamp":  "2026-03-15T20:53:08Z",
              "event":  "Scan",
              "ScanType":  "AutoScan",
              "BodyName":  "Fachia BP-A d13 B",
              "BodyID":  3,
              "Parents":  [
                              "@{Null=1}",
                              "@{Null=0}"
                          ],
              "StarSystem":  "Fachia BP-A d13",
              "SystemAddress":  459955559171,
              "DistanceFromArrivalLS":  248.015354,
              "StarType":  "M",
              "Subclass":  2,
              "StellarMass":  0.410156,
              "Radius":  438189600.000000,
              "AbsoluteMagnitude":  8.386780,
              "Age_MY":  8404,
              "SurfaceTemperature":  3210.000000,
              "Luminosity":  "Va",
              "SemiMajorAxis":  53605358600.616455,
              "Eccentricity":  0.120425,
              "OrbitalInclination":  35.560528,
              "Periapsis":  263.705831,
              "OrbitalPeriod":  12658608.555794,
              "AscendingNode":  -96.236139,
              "MeanAnomaly":  359.186214,
              "RotationPeriod":  211534.520213,
              "AxialTilt":  0.000000,
              "WasDiscovered":  false,
              "WasMapped":  false,
              "WasFootfalled":  false
          },
    "20":  {
               "timestamp":  "2026-03-15T20:54:40Z",
               "event":  "Scan",
               "ScanType":  "AutoScan",
               "BodyName":  "Fachia BP-A d13 C A Belt Cluster 6",
               "BodyID":  20,
               "Parents":  [
                               "@{Ring=14}",
                               "@{Star=4}",
                               "@{Null=0}"
                           ],
               "StarSystem":  "Fachia BP-A d13",
               "SystemAddress":  459955559171,
               "DistanceFromArrivalLS":  90411.338710,
               "WasDiscovered":  false,
               "WasMapped":  false,
               "WasFootfalled":  false
           },
    "12":  {
               "timestamp":  "2026-03-15T20:55:33Z",
               "event":  "Scan",
               "ScanType":  "Detailed",
               "BodyName":  "Fachia BP-A d13 AB 6",
               "BodyID":  12,
               "Parents":  [
                               "@{Null=1}",
                               "@{Null=0}"
                           ],
               "StarSystem":  "Fachia BP-A d13",
               "SystemAddress":  459955559171,
               "DistanceFromArrivalLS":  4008.853336,
               "TidalLock":  false,
               "TerraformState":  "",
               "PlanetClass":  "High metal content body",
               "Atmosphere":  "hot thick carbon dioxide atmosphere",
               "AtmosphereType":  "CarbonDioxide",
               "AtmosphereComposition":  [
                                             "@{Name=CarbonDioxide; Percent=99.009674}",
                                             "@{Name=SulphurDioxide; Percent=0.990097}"
                                         ],
               "Volcanism":  "",
               "MassEM":  1.851134,
               "Radius":  7270953.000000,
               "SurfaceGravity":  13.956120,
               "SurfaceTemperature":  1592.834961,
               "SurfacePressure":  27841426.000000,
               "Landable":  false,
               "Composition":  {
                                   "Ice":  0.000000,
                                   "Rock":  0.662999,
                                   "Metal":  0.337001
                               },
               "SemiMajorAxis":  1210969805717.468262,
               "Eccentricity":  0.009837,
               "OrbitalInclination":  0.184010,
               "Periapsis":  300.673895,
               "OrbitalPeriod":  686363464.593887,
               "AscendingNode":  -78.971351,
               "MeanAnomaly":  181.810670,
               "RotationPeriod":  79784.125588,
               "AxialTilt":  -2.633838,
               "WasDiscovered":  false,
               "WasMapped":  false,
               "WasFootfalled":  false
           },
    "10":  {
               "timestamp":  "2026-03-15T20:54:56Z",
               "event":  "Scan",
               "ScanType":  "Detailed",
               "BodyName":  "Fachia BP-A d13 AB 4",
               "BodyID":  10,
               "Parents":  [
                               "@{Null=9}",
                               "@{Null=1}",
                               "@{Null=0}"
                           ],
               "StarSystem":  "Fachia BP-A d13",
               "SystemAddress":  459955559171,
               "DistanceFromArrivalLS":  3020.741259,
               "TidalLock":  false,
               "TerraformState":  "",
               "PlanetClass":  "High metal content body",
               "Atmosphere":  "",
               "AtmosphereType":  "None",
               "Volcanism":  "",
               "MassEM":  0.535939,
               "Radius":  5036281.000000,
               "SurfaceGravity":  8.421802,
               "SurfaceTemperature":  569.135803,
               "SurfacePressure":  0.000000,
               "Landable":  true,
               "Materials":  [
                                 "@{Name=iron; Percent=21.136309}",
                                 "@{Name=nickel; Percent=15.986618}",
                                 "@{Name=sulphur; Percent=15.002287}",
                                 "@{Name=carbon; Percent=12.615368}",
                                 "@{Name=chromium; Percent=9.505699}",
                                 "@{Name=manganese; Percent=8.729080}",
                                 "@{Name=phosphorus; Percent=8.076576}",
                                 "@{Name=vanadium; Percent=5.190341}",
                                 "@{Name=niobium; Percent=1.444554}",
                                 "@{Name=molybdenum; Percent=1.380189}",
                                 "@{Name=antimony; Percent=0.932977}"
                             ],
               "Composition":  {
                                   "Ice":  0.000000,
                                   "Rock":  0.669877,
                                   "Metal":  0.330123
                               },
               "SemiMajorAxis":  746383529.901505,
               "Eccentricity":  0.078017,
               "OrbitalInclination":  3.125115,
               "Periapsis":  97.486204,
               "OrbitalPeriod":  26091095.805168,
               "AscendingNode":  -168.747022,
               "MeanAnomaly":  111.991375,
               "RotationPeriod":  76319.843095,
               "AxialTilt":  -0.346869,
               "WasDiscovered":  false,
               "WasMapped":  false,
               "WasFootfalled":  false
           },
    "17":  {
               "timestamp":  "2026-03-15T20:54:40Z",
               "event":  "Scan",
               "ScanType":  "AutoScan",
               "BodyName":  "Fachia BP-A d13 C A Belt Cluster 3",
               "BodyID":  17,
               "Parents":  [
                               "@{Ring=14}",
                               "@{Star=4}",
                               "@{Null=0}"
                           ],
               "StarSystem":  "Fachia BP-A d13",
               "SystemAddress":  459955559171,
               "DistanceFromArrivalLS":  90413.332182,
               "WasDiscovered":  false,
               "WasMapped":  false,
               "WasFootfalled":  false
           },
    "13":  {
               "timestamp":  "2026-03-15T20:55:29Z",
               "event":  "Scan",
               "ScanType":  "Detailed",
               "BodyName":  "Fachia BP-A d13 AB 6 a",
               "BodyID":  13,
               "Parents":  [
                               "@{Planet=12}",
                               "@{Null=1}",
                               "@{Null=0}"
                           ],
               "StarSystem":  "Fachia BP-A d13",
               "SystemAddress":  459955559171,
               "DistanceFromArrivalLS":  4012.643907,
               "TidalLock":  false,
               "TerraformState":  "",
               "PlanetClass":  "Rocky body",
               "Atmosphere":  "",
               "AtmosphereType":  "None",
               "Volcanism":  "",
               "MassEM":  0.067021,
               "Radius":  2755270.250000,
               "SurfaceGravity":  3.518764,
               "SurfaceTemperature":  485.781189,
               "SurfacePressure":  0.000000,
               "Landable":  true,
               "Materials":  [
                                 "@{Name=iron; Percent=19.326305}",
                                 "@{Name=sulphur; Percent=17.305206}",
                                 "@{Name=nickel; Percent=14.617607}",
                                 "@{Name=carbon; Percent=14.551886}",
                                 "@{Name=phosphorus; Percent=9.316367}",
                                 "@{Name=chromium; Percent=8.691681}",
                                 "@{Name=manganese; Percent=7.981567}",
                                 "@{Name=germanium; Percent=5.089002}",
                                 "@{Name=tin; Percent=1.200236}",
                                 "@{Name=antimony; Percent=1.076193}",
                                 "@{Name=mercury; Percent=0.843948}"
                             ],
               "Composition":  {
                                   "Ice":  0.000000,
                                   "Rock":  0.860051,
                                   "Metal":  0.139949
                               },
               "SemiMajorAxis":  4323891758.918762,
               "Eccentricity":  0.000000,
               "OrbitalInclination":  -75.191558,
               "Periapsis":  8.433323,
               "OrbitalPeriod":  64608691.930771,
               "AscendingNode":  72.887066,
               "MeanAnomaly":  178.119744,
               "RotationPeriod":  84020.368312,
               "AxialTilt":  0.219089,
               "WasDiscovered":  false,
               "WasMapped":  false,
               "WasFootfalled":  false
           },
    "27":  {
               "timestamp":  "2026-03-15T20:53:39Z",
               "event":  "ScanBaryCentre",
               "StarSystem":  "Fachia BP-A d13",
               "SystemAddress":  459955559171,
               "BodyID":  27,
               "SemiMajorAxis":  437819826602.935791,
               "Eccentricity":  0.005770,
               "OrbitalInclination":  -0.100585,
               "Periapsis":  268.696551,
               "OrbitalPeriod":  313530045.747757,
               "AscendingNode":  -42.054752,
               "MeanAnomaly":  74.363168
           },
    "30":  {
               "timestamp":  "2026-03-15T20:53:57Z",
               "event":  "Scan",
               "ScanType":  "Detailed",
               "BodyName":  "Fachia BP-A d13 C 8",
               "BodyID":  30,
               "Parents":  [
                               "@{Star=4}",
                               "@{Null=0}"
                           ],
               "StarSystem":  "Fachia BP-A d13",
               "SystemAddress":  459955559171,
               "DistanceFromArrivalLS":  90782.900446,
               "TidalLock":  false,
               "TerraformState":  "",
               "PlanetClass":  "Rocky ice body",
               "Atmosphere":  "thick argon rich atmosphere",
               "AtmosphereType":  "ArgonRich",
               "AtmosphereComposition":  [
                                             "@{Name=Nitrogen; Percent=99.009735}",
                                             "@{Name=Argon; Percent=0.990064}"
                                         ],
               "Volcanism":  "major water magma volcanism",
               "MassEM":  0.711427,
               "Radius":  6536501.500000,
               "SurfaceGravity":  6.636648,
               "SurfaceTemperature":  167.229385,
               "SurfacePressure":  125917152.000000,
               "Landable":  false,
               "Composition":  {
                                   "Ice":  0.464095,
                                   "Rock":  0.356631,
                                   "Metal":  0.179274
                               },
               "SemiMajorAxis":  594687563180.923462,
               "Eccentricity":  0.005077,
               "OrbitalInclination":  0.394336,
               "Periapsis":  204.484956,
               "OrbitalPeriod":  496328604.221344,
               "AscendingNode":  4.713162,
               "MeanAnomaly":  66.698233,
               "RotationPeriod":  96407.207163,
               "AxialTilt":  -0.164864,
               "WasDiscovered":  false,
               "WasMapped":  false,
               "WasFootfalled":  false
           },
    "18":  {
               "timestamp":  "2026-03-15T20:54:40Z",
               "event":  "Scan",
               "ScanType":  "AutoScan",
               "BodyName":  "Fachia BP-A d13 C A Belt Cluster 4",
               "BodyID":  18,
               "Parents":  [
                               "@{Ring=14}",
                               "@{Star=4}",
                               "@{Null=0}"
                           ],
               "StarSystem":  "Fachia BP-A d13",
               "SystemAddress":  459955559171,
               "DistanceFromArrivalLS":  90415.155078,
               "WasDiscovered":  false,
               "WasMapped":  false,
               "WasFootfalled":  false
           },
    "29":  {
               "timestamp":  "2026-03-15T20:53:46Z",
               "event":  "Scan",
               "ScanType":  "Detailed",
               "BodyName":  "Fachia BP-A d13 C 7",
               "BodyID":  29,
               "Parents":  [
                               "@{Null=27}",
                               "@{Star=4}",
                               "@{Null=0}"
                           ],
               "StarSystem":  "Fachia BP-A d13",
               "SystemAddress":  459955559171,
               "DistanceFromArrivalLS":  90437.509511,
               "TidalLock":  false,
               "TerraformState":  "",
               "PlanetClass":  "High metal content body",
               "Atmosphere":  "thin nitrogen atmosphere",
               "AtmosphereType":  "Nitrogen",
               "AtmosphereComposition":  [
                                             "@{Name=Nitrogen; Percent=100.000000}"
                                         ],
               "Volcanism":  "",
               "MassEM":  0.104246,
               "Radius":  3030519.750000,
               "SurfaceGravity":  4.524135,
               "SurfaceTemperature":  136.025024,
               "SurfacePressure":  542.566345,
               "Landable":  true,
               "Materials":  [
                                 "@{Name=iron; Percent=22.435467}",
                                 "@{Name=nickel; Percent=16.969248}",
                                 "@{Name=sulphur; Percent=16.201698}",
                                 "@{Name=carbon; Percent=13.623951}",
                                 "@{Name=chromium; Percent=10.089974}",
                                 "@{Name=phosphorus; Percent=8.722287}",
                                 "@{Name=zinc; Percent=6.097120}",
                                 "@{Name=arsenic; Percent=2.130745}",
                                 "@{Name=cadmium; Percent=1.742216}",
                                 "@{Name=antimony; Percent=1.007567}",
                                 "@{Name=mercury; Percent=0.979720}"
                             ],
               "Composition":  {
                                   "Ice":  0.000000,
                                   "Rock":  0.686616,
                                   "Metal":  0.313384
                               },
               "SemiMajorAxis":  748695850.372314,
               "Eccentricity":  0.149866,
               "OrbitalInclination":  -4.249907,
               "Periapsis":  144.243685,
               "OrbitalPeriod":  19437147.378922,
               "AscendingNode":  91.617630,
               "MeanAnomaly":  330.438266,
               "RotationPeriod":  40556.336011,
               "AxialTilt":  -0.240668,
               "WasDiscovered":  false,
               "WasMapped":  false,
               "WasFootfalled":  false
           },
    "19":  {
               "timestamp":  "2026-03-15T20:54:40Z",
               "event":  "Scan",
               "ScanType":  "AutoScan",
               "BodyName":  "Fachia BP-A d13 C A Belt Cluster 5",
               "BodyID":  19,
               "Parents":  [
                               "@{Ring=14}",
                               "@{Star=4}",
                               "@{Null=0}"
                           ],
               "StarSystem":  "Fachia BP-A d13",
               "SystemAddress":  459955559171,
               "DistanceFromArrivalLS":  90410.271240,
               "WasDiscovered":  false,
               "WasMapped":  false,
               "WasFootfalled":  false
           },
    "1":  {
              "timestamp":  "2026-03-15T20:53:06Z",
              "event":  "ScanBaryCentre",
              "StarSystem":  "Fachia BP-A d13",
              "SystemAddress":  459955559171,
              "BodyID":  1,
              "SemiMajorAxis":  5952971279621.124023,
              "Eccentricity":  0.248509,
              "OrbitalInclination":  -19.060700,
              "Periapsis":  333.867611,
              "OrbitalPeriod":  85125939249.992371,
              "AscendingNode":  -166.951120,
              "MeanAnomaly":  320.815210
          },
    "5":  {
              "timestamp":  "2026-03-15T20:55:21Z",
              "event":  "Scan",
              "ScanType":  "Detailed",
              "BodyName":  "Fachia BP-A d13 AB 1",
              "BodyID":  5,
              "Parents":  [
                              "@{Null=1}",
                              "@{Null=0}"
                          ],
              "StarSystem":  "Fachia BP-A d13",
              "SystemAddress":  459955559171,
              "DistanceFromArrivalLS":  844.543930,
              "TidalLock":  false,
              "TerraformState":  "",
              "PlanetClass":  "Metal rich body",
              "Atmosphere":  "",
              "AtmosphereType":  "None",
              "Volcanism":  "",
              "MassEM":  0.408599,
              "Radius":  3709431.000000,
              "SurfaceGravity":  11.835637,
              "SurfaceTemperature":  1037.755737,
              "SurfacePressure":  0.000000,
              "Landable":  true,
              "Materials":  [
                                "@{Name=iron; Percent=37.200684}",
                                "@{Name=nickel; Percent=28.137037}",
                                "@{Name=manganese; Percent=15.363503}",
                                "@{Name=vanadium; Percent=9.135193}",
                                "@{Name=zirconium; Percent=4.319766}",
                                "@{Name=cadmium; Percent=2.888802}",
                                "@{Name=mercury; Percent=1.624493}",
                                "@{Name=technetium; Percent=1.330518}"
                            ],
              "Composition":  {
                                  "Ice":  0.000000,
                                  "Rock":  0.000000,
                                  "Metal":  1.000000
                              },
              "SemiMajorAxis":  262461632490.158081,
              "Eccentricity":  0.000020,
              "OrbitalInclination":  0.016732,
              "Periapsis":  220.088154,
              "OrbitalPeriod":  69255286.455154,
              "AscendingNode":  -86.685459,
              "MeanAnomaly":  65.106566,
              "RotationPeriod":  89268.421425,
              "AxialTilt":  0.362144,
              "WasDiscovered":  false,
              "WasMapped":  false,
              "WasFootfalled":  false
          },
    "23":  {
               "timestamp":  "2026-03-15T20:54:29Z",
               "event":  "Scan",
               "ScanType":  "Detailed",
               "BodyName":  "Fachia BP-A d13 C 3",
               "BodyID":  23,
               "Parents":  [
                               "@{Star=4}",
                               "@{Null=0}"
                           ],
               "StarSystem":  "Fachia BP-A d13",
               "SystemAddress":  459955559171,
               "DistanceFromArrivalLS":  90806.755178,
               "TidalLock":  false,
               "TerraformState":  "",
               "PlanetClass":  "High metal content body",
               "Atmosphere":  "carbon dioxide atmosphere",
               "AtmosphereType":  "CarbonDioxide",
               "AtmosphereComposition":  [
                                             "@{Name=CarbonDioxide; Percent=98.183151}",
                                             "@{Name=SulphurDioxide; Percent=1.816847}"
                                         ],
               "Volcanism":  "",
               "MassEM":  0.098607,
               "Radius":  2963414.250000,
               "SurfaceGravity":  4.475416,
               "SurfaceTemperature":  240.633072,
               "SurfacePressure":  15764.811523,
               "Landable":  false,
               "Composition":  {
                                   "Ice":  0.000000,
                                   "Rock":  0.669878,
                                   "Metal":  0.330122
                               },
               "SemiMajorAxis":  123924571275.711060,
               "Eccentricity":  0.001671,
               "OrbitalInclination":  -0.473944,
               "Periapsis":  125.487466,
               "OrbitalPeriod":  47214148.044586,
               "AscendingNode":  156.426273,
               "MeanAnomaly":  238.219118,
               "RotationPeriod":  124362.850560,
               "AxialTilt":  -0.035190,
               "WasDiscovered":  false,
               "WasMapped":  false,
               "WasFootfalled":  false
           },
    "8":  {
              "timestamp":  "2026-03-15T20:55:14Z",
              "event":  "Scan",
              "ScanType":  "Detailed",
              "BodyName":  "Fachia BP-A d13 AB 3 a",
              "BodyID":  8,
              "Parents":  [
                              "@{Planet=7}",
                              "@{Null=1}",
                              "@{Null=0}"
                          ],
              "StarSystem":  "Fachia BP-A d13",
              "SystemAddress":  459955559171,
              "DistanceFromArrivalLS":  2271.867776,
              "TidalLock":  false,
              "TerraformState":  "",
              "PlanetClass":  "Rocky body",
              "Atmosphere":  "",
              "AtmosphereType":  "None",
              "Volcanism":  "",
              "MassEM":  0.037455,
              "Radius":  2283371.000000,
              "SurfaceGravity":  2.863317,
              "SurfaceTemperature":  655.796997,
              "SurfacePressure":  0.000000,
              "Landable":  true,
              "Materials":  [
                                "@{Name=iron; Percent=19.805702}",
                                "@{Name=sulphur; Percent=17.734360}",
                                "@{Name=nickel; Percent=14.980203}",
                                "@{Name=carbon; Percent=14.912759}",
                                "@{Name=phosphorus; Percent=9.547404}",
                                "@{Name=manganese; Percent=8.179553}",
                                "@{Name=zinc; Percent=5.382448}",
                                "@{Name=germanium; Percent=5.215205}",
                                "@{Name=cadmium; Percent=1.538002}",
                                "@{Name=niobium; Percent=1.353614}",
                                "@{Name=tellurium; Percent=1.350749}"
                            ],
              "Composition":  {
                                  "Ice":  0.000000,
                                  "Rock":  0.860047,
                                  "Metal":  0.139953
                              },
              "SemiMajorAxis":  1595391929.149628,
              "Eccentricity":  0.000000,
              "OrbitalInclination":  40.505655,
              "Periapsis":  60.916463,
              "OrbitalPeriod":  19902486.205101,
              "AscendingNode":  -47.825524,
              "MeanAnomaly":  309.638465,
              "RotationPeriod":  269019.073041,
              "AxialTilt":  -0.019180,
              "WasDiscovered":  false,
              "WasMapped":  false,
              "WasFootfalled":  false
          },
    "26":  {
               "Signals":  [
                               "@{Type=$SAA_SignalType_Biological;; Type_Localised=Biological; Count=4}"
                           ],
               "timestamp":  "2026-03-15T20:53:33Z",
               "event":  "Scan",
               "ScanType":  "Detailed",
               "BodyName":  "Fachia BP-A d13 C 5 a",
               "BodyID":  26,
               "Parents":  [
                               "@{Planet=25}",
                               "@{Star=4}",
                               "@{Null=0}"
                           ],
               "StarSystem":  "Fachia BP-A d13",
               "SystemAddress":  459955559171,
               "DistanceFromArrivalLS":  91267.663032,
               "TidalLock":  false,
               "TerraformState":  "",
               "PlanetClass":  "Rocky body",
               "Atmosphere":  "thin carbon dioxide atmosphere",
               "AtmosphereType":  "CarbonDioxide",
               "AtmosphereComposition":  [
                                             "@{Name=CarbonDioxide; Percent=99.009911}",
                                             "@{Name=SulphurDioxide; Percent=0.990099}"
                                         ],
               "Volcanism":  "",
               "MassEM":  0.008637,
               "Radius":  1414822.750000,
               "SurfaceGravity":  1.719789,
               "SurfaceTemperature":  182.162460,
               "SurfacePressure":  5484.521973,
               "Landable":  true,
               "Materials":  [
                                 "@{Name=iron; Percent=20.568729}",
                                 "@{Name=sulphur; Percent=18.417593}",
                                 "@{Name=nickel; Percent=15.557326}",
                                 "@{Name=carbon; Percent=15.487287}",
                                 "@{Name=phosphorus; Percent=9.915227}",
                                 "@{Name=zinc; Percent=5.589811}",
                                 "@{Name=germanium; Percent=5.416126}",
                                 "@{Name=vanadium; Percent=5.050965}",
                                 "@{Name=cadmium; Percent=1.597255}",
                                 "@{Name=ruthenium; Percent=1.270250}",
                                 "@{Name=tungsten; Percent=1.129430}"
                             ],
               "Composition":  {
                                   "Ice":  0.000000,
                                   "Rock":  0.860048,
                                   "Metal":  0.139952
                               },
               "SemiMajorAxis":  780657255.649567,
               "Eccentricity":  0.000000,
               "OrbitalInclination":  -87.966037,
               "Periapsis":  13.327342,
               "OrbitalPeriod":  13365279.436111,
               "AscendingNode":  29.170905,
               "MeanAnomaly":  140.927256,
               "RotationPeriod":  195184.540488,
               "AxialTilt":  0.175952,
               "WasDiscovered":  false,
               "WasMapped":  false,
               "WasFootfalled":  false
           },
    "22":  {
               "Signals":  [
                               "@{Type=$SAA_SignalType_Biological;; Type_Localised=Biological; Count=1}"
                           ],
               "timestamp":  "2026-03-15T20:54:12Z",
               "event":  "Scan",
               "ScanType":  "Detailed",
               "BodyName":  "Fachia BP-A d13 C 2",
               "BodyID":  22,
               "Parents":  [
                               "@{Star=4}",
                               "@{Null=0}"
                           ],
               "StarSystem":  "Fachia BP-A d13",
               "SystemAddress":  459955559171,
               "DistanceFromArrivalLS":  90654.896883,
               "TidalLock":  false,
               "TerraformState":  "",
               "PlanetClass":  "High metal content body",
               "Atmosphere":  "thin sulfur dioxide atmosphere",
               "AtmosphereType":  "SulphurDioxide",
               "AtmosphereComposition":  [
                                             "@{Name=SulphurDioxide; Percent=100.000000}"
                                         ],
               "Volcanism":  "",
               "MassEM":  0.067778,
               "Radius":  2628181.750000,
               "SurfaceGravity":  3.911005,
               "SurfaceTemperature":  186.828796,
               "SurfacePressure":  218.734528,
               "Landable":  true,
               "Materials":  [
                                 "@{Name=iron; Percent=22.238468}",
                                 "@{Name=nickel; Percent=16.820246}",
                                 "@{Name=sulphur; Percent=15.784606}",
                                 "@{Name=carbon; Percent=13.273220}",
                                 "@{Name=manganese; Percent=9.184260}",
                                 "@{Name=phosphorus; Percent=8.497743}",
                                 "@{Name=vanadium; Percent=5.460994}",
                                 "@{Name=germanium; Percent=4.641834}",
                                 "@{Name=molybdenum; Percent=1.452159}",
                                 "@{Name=tin; Percent=1.444216}",
                                 "@{Name=tellurium; Percent=1.202245}"
                             ],
               "Composition":  {
                                   "Ice":  0.000000,
                                   "Rock":  0.669878,
                                   "Metal":  0.330122
                               },
               "SemiMajorAxis":  91671501994.132996,
               "Eccentricity":  0.000683,
               "OrbitalInclination":  -0.617191,
               "Periapsis":  47.501958,
               "OrbitalPeriod":  30039144.158363,
               "AscendingNode":  1.204804,
               "MeanAnomaly":  308.709108,
               "RotationPeriod":  186524.358881,
               "AxialTilt":  -0.419101,
               "WasDiscovered":  false,
               "WasMapped":  false,
               "WasFootfalled":  false
           },
    "28":  {
               "timestamp":  "2026-03-15T20:53:39Z",
               "event":  "Scan",
               "ScanType":  "Detailed",
               "BodyName":  "Fachia BP-A d13 C 6",
               "BodyID":  28,
               "Parents":  [
                               "@{Null=27}",
                               "@{Star=4}",
                               "@{Null=0}"
                           ],
               "StarSystem":  "Fachia BP-A d13",
               "SystemAddress":  459955559171,
               "DistanceFromArrivalLS":  90436.908718,
               "TidalLock":  false,
               "TerraformState":  "",
               "PlanetClass":  "High metal content body",
               "Atmosphere":  "nitrogen atmosphere",
               "AtmosphereType":  "Nitrogen",
               "AtmosphereComposition":  [
                                             "@{Name=Nitrogen; Percent=99.966446}"
                                         ],
               "Volcanism":  "",
               "MassEM":  0.231454,
               "Radius":  3874121.250000,
               "SurfaceGravity":  6.146507,
               "SurfaceTemperature":  140.944153,
               "SurfacePressure":  63917.804688,
               "Landable":  false,
               "Composition":  {
                                   "Ice":  0.000000,
                                   "Rock":  0.662334,
                                   "Metal":  0.337666
                               },
               "SemiMajorAxis":  337209939.956665,
               "Eccentricity":  0.149866,
               "OrbitalInclination":  -4.249907,
               "Periapsis":  324.243679,
               "OrbitalPeriod":  19437147.378922,
               "AscendingNode":  91.617630,
               "MeanAnomaly":  330.438147,
               "RotationPeriod":  153756.648054,
               "AxialTilt":  -1.644332,
               "WasDiscovered":  false,
               "WasMapped":  false,
               "WasFootfalled":  false
           },
    "4":  {
              "timestamp":  "2026-03-15T20:53:08Z",
              "event":  "Scan",
              "ScanType":  "AutoScan",
              "BodyName":  "Fachia BP-A d13 C",
              "BodyID":  4,
              "Parents":  [
                              "@{Null=0}"
                          ],
              "StarSystem":  "Fachia BP-A d13",
              "SystemAddress":  459955559171,
              "DistanceFromArrivalLS":  90413.737055,
              "StarType":  "M",
              "Subclass":  6,
              "StellarMass":  0.253906,
              "Radius":  293138112.000000,
              "AbsoluteMagnitude":  10.183838,
              "Age_MY":  8404,
              "SurfaceTemperature":  2595.000000,
              "Luminosity":  "Va",
              "SemiMajorAxis":  26284365653991.699219,
              "Eccentricity":  0.248509,
              "OrbitalInclination":  -19.060700,
              "Periapsis":  153.867616,
              "OrbitalPeriod":  85125939249.992371,
              "AscendingNode":  -166.951120,
              "MeanAnomaly":  320.815210,
              "RotationPeriod":  123705.802591,
              "AxialTilt":  0.000000,
              "Rings":  [
                            "@{Name=Fachia BP-A d13 C A Belt; RingClass=eRingClass_MetalRich; MassMT=66921000000000; InnerRad=448700000; OuterRad=1528000000}"
                        ],
              "WasDiscovered":  false,
              "WasMapped":  false,
              "WasFootfalled":  false
          },
    "25":  {
               "timestamp":  "2026-03-15T20:53:29Z",
               "event":  "Scan",
               "ScanType":  "Detailed",
               "BodyName":  "Fachia BP-A d13 C 5",
               "BodyID":  25,
               "Parents":  [
                               "@{Star=4}",
                               "@{Null=0}"
                           ],
               "StarSystem":  "Fachia BP-A d13",
               "SystemAddress":  459955559171,
               "DistanceFromArrivalLS":  91267.136660,
               "TidalLock":  false,
               "TerraformState":  "",
               "PlanetClass":  "High metal content body",
               "Atmosphere":  "carbon dioxide atmosphere",
               "AtmosphereType":  "CarbonDioxide",
               "AtmosphereComposition":  [
                                             "@{Name=CarbonDioxide; Percent=81.663132}",
                                             "@{Name=Nitrogen; Percent=17.513863}",
                                             "@{Name=SulphurDioxide; Percent=0.816631}"
                                         ],
               "Volcanism":  "",
               "MassEM":  0.255158,
               "Radius":  3995485.500000,
               "SurfaceGravity":  6.370581,
               "SurfaceTemperature":  231.117737,
               "SurfacePressure":  84214.296875,
               "Landable":  false,
               "Composition":  {
                                   "Ice":  0.000000,
                                   "Rock":  0.663440,
                                   "Metal":  0.336560
                               },
               "SemiMajorAxis":  316078829765.319824,
               "Eccentricity":  0.001800,
               "OrbitalInclination":  -0.184101,
               "Periapsis":  103.244675,
               "OrbitalPeriod":  192322087.287903,
               "AscendingNode":  -90.554829,
               "MeanAnomaly":  274.654690,
               "RotationPeriod":  123983.076835,
               "AxialTilt":  -2.560077,
               "WasDiscovered":  false,
               "WasMapped":  false,
               "WasFootfalled":  false
           },
    "9":  {
              "timestamp":  "2026-03-15T20:54:56Z",
              "event":  "ScanBaryCentre",
              "StarSystem":  "Fachia BP-A d13",
              "SystemAddress":  459955559171,
              "BodyID":  9,
              "SemiMajorAxis":  879568970203.399658,
              "Eccentricity":  0.008352,
              "OrbitalInclination":  0.531343,
              "Periapsis":  353.181600,
              "OrbitalPeriod":  424872893.095016,
              "AscendingNode":  -20.509631,
              "MeanAnomaly":  116.152442
          },
    "33":  {
               "timestamp":  "2026-03-15T20:53:21Z",
               "event":  "Scan",
               "ScanType":  "Detailed",
               "BodyName":  "Fachia BP-A d13 C 10",
               "BodyID":  33,
               "Parents":  [
                               "@{Star=4}",
                               "@{Null=0}"
                           ],
               "StarSystem":  "Fachia BP-A d13",
               "SystemAddress":  459955559171,
               "DistanceFromArrivalLS":  86768.315565,
               "TidalLock":  false,
               "TerraformState":  "",
               "PlanetClass":  "Icy body",
               "Atmosphere":  "thick argon rich atmosphere",
               "AtmosphereType":  "ArgonRich",
               "AtmosphereComposition":  [
                                             "@{Name=Nitrogen; Percent=98.984459}",
                                             "@{Name=Argon; Percent=0.989845}"
                                         ],
               "Volcanism":  "",
               "MassEM":  0.242802,
               "Radius":  4859898.500000,
               "SurfaceGravity":  4.097382,
               "SurfaceTemperature":  112.314697,
               "SurfacePressure":  593583.375000,
               "Landable":  false,
               "Composition":  {
                                   "Ice":  0.573798,
                                   "Rock":  0.285502,
                                   "Metal":  0.140700
                               },
               "SemiMajorAxis":  1096733927726.745605,
               "Eccentricity":  0.000852,
               "OrbitalInclination":  0.115662,
               "Periapsis":  0.416327,
               "OrbitalPeriod":  1243048131.465912,
               "AscendingNode":  -161.905741,
               "MeanAnomaly":  320.725782,
               "RotationPeriod":  157648.989847,
               "AxialTilt":  -0.079090,
               "WasDiscovered":  false,
               "WasMapped":  false,
               "WasFootfalled":  false
           },
    "15":  {
               "timestamp":  "2026-03-15T20:54:40Z",
               "event":  "Scan",
               "ScanType":  "AutoScan",
               "BodyName":  "Fachia BP-A d13 C A Belt Cluster 1",
               "BodyID":  15,
               "Parents":  [
                               "@{Ring=14}",
                               "@{Star=4}",
                               "@{Null=0}"
                           ],
               "StarSystem":  "Fachia BP-A d13",
               "SystemAddress":  459955559171,
               "DistanceFromArrivalLS":  90414.789378,
               "WasDiscovered":  false,
               "WasMapped":  false,
               "WasFootfalled":  false
           },
    "21":  {
               "timestamp":  "2026-03-15T20:54:32Z",
               "event":  "Scan",
               "ScanType":  "Detailed",
               "BodyName":  "Fachia BP-A d13 C 1",
               "BodyID":  21,
               "Parents":  [
                               "@{Star=4}",
                               "@{Null=0}"
                           ],
               "StarSystem":  "Fachia BP-A d13",
               "SystemAddress":  459955559171,
               "DistanceFromArrivalLS":  90653.544230,
               "TidalLock":  false,
               "TerraformState":  "",
               "PlanetClass":  "High metal content body",
               "Atmosphere":  "carbon dioxide atmosphere",
               "AtmosphereType":  "CarbonDioxide",
               "AtmosphereComposition":  [
                                             "@{Name=CarbonDioxide; Percent=97.570259}",
                                             "@{Name=SulphurDioxide; Percent=2.429740}"
                                         ],
               "Volcanism":  "",
               "MassEM":  0.114143,
               "Radius":  3104910.500000,
               "SurfaceGravity":  4.719099,
               "SurfaceTemperature":  267.672852,
               "SurfacePressure":  13106.859375,
               "Landable":  false,
               "Composition":  {
                                   "Ice":  0.000000,
                                   "Rock":  0.669878,
                                   "Metal":  0.330122
                               },
               "SemiMajorAxis":  75098944306.373596,
               "Eccentricity":  0.000018,
               "OrbitalInclination":  0.163770,
               "Periapsis":  338.934344,
               "OrbitalPeriod":  22273407.578468,
               "AscendingNode":  -134.966590,
               "MeanAnomaly":  158.696165,
               "RotationPeriod":  309808.212122,
               "AxialTilt":  -0.470787,
               "WasDiscovered":  false,
               "WasMapped":  false,
               "WasFootfalled":  false
           },
    "24":  {
               "timestamp":  "2026-03-15T20:54:15Z",
               "event":  "Scan",
               "ScanType":  "Detailed",
               "BodyName":  "Fachia BP-A d13 C 4",
               "BodyID":  24,
               "Parents":  [
                               "@{Star=4}",
                               "@{Null=0}"
                           ],
               "StarSystem":  "Fachia BP-A d13",
               "SystemAddress":  459955559171,
               "DistanceFromArrivalLS":  91171.480565,
               "TidalLock":  false,
               "TerraformState":  "",
               "PlanetClass":  "High metal content body",
               "Atmosphere":  "thin carbon dioxide atmosphere",
               "AtmosphereType":  "CarbonDioxide",
               "AtmosphereComposition":  [
                                             "@{Name=CarbonDioxide; Percent=92.791740}",
                                             "@{Name=SulphurDioxide; Percent=7.208257}"
                                         ],
               "Volcanism":  "",
               "MassEM":  0.115653,
               "Radius":  3117930.500000,
               "SurfaceGravity":  4.741689,
               "SurfaceTemperature":  183.086487,
               "SurfacePressure":  2912.344971,
               "Landable":  true,
               "Materials":  [
                                 "@{Name=iron; Percent=22.107357}",
                                 "@{Name=nickel; Percent=16.721077}",
                                 "@{Name=sulphur; Percent=15.691529}",
                                 "@{Name=carbon; Percent=13.194950}",
                                 "@{Name=manganese; Percent=9.130113}",
                                 "@{Name=phosphorus; Percent=8.447634}",
                                 "@{Name=zinc; Percent=6.007952}",
                                 "@{Name=vanadium; Percent=5.428797}",
                                 "@{Name=tin; Percent=1.435701}",
                                 "@{Name=tungsten; Percent=1.213916}",
                                 "@{Name=polonium; Percent=0.620985}"
                             ],
               "Composition":  {
                                   "Ice":  0.000000,
                                   "Rock":  0.669877,
                                   "Metal":  0.330123
                               },
               "SemiMajorAxis":  235041636228.561401,
               "Eccentricity":  0.001830,
               "OrbitalInclination":  -0.005876,
               "Periapsis":  164.258407,
               "OrbitalPeriod":  123325598.239899,
               "AscendingNode":  -142.983136,
               "MeanAnomaly":  333.847363,
               "RotationPeriod":  113092.282607,
               "AxialTilt":  0.389592,
               "WasDiscovered":  false,
               "WasMapped":  false,
               "WasFootfalled":  false
           },
    "16":  {
               "timestamp":  "2026-03-15T20:54:40Z",
               "event":  "Scan",
               "ScanType":  "AutoScan",
               "BodyName":  "Fachia BP-A d13 C A Belt Cluster 2",
               "BodyID":  16,
               "Parents":  [
                               "@{Ring=14}",
                               "@{Star=4}",
                               "@{Null=0}"
                           ],
               "StarSystem":  "Fachia BP-A d13",
               "SystemAddress":  459955559171,
               "DistanceFromArrivalLS":  90415.763273,
               "WasDiscovered":  false,
               "WasMapped":  false,
               "WasFootfalled":  false
           },
    "32":  {
               "timestamp":  "2026-03-15T20:54:20Z",
               "event":  "Scan",
               "ScanType":  "Detailed",
               "BodyName":  "Fachia BP-A d13 C 9",
               "BodyID":  32,
               "Parents":  [
                               "@{Star=4}",
                               "@{Null=0}"
                           ],
               "StarSystem":  "Fachia BP-A d13",
               "SystemAddress":  459955559171,
               "DistanceFromArrivalLS":  92656.006326,
               "TidalLock":  false,
               "TerraformState":  "",
               "PlanetClass":  "Icy body",
               "Atmosphere":  "thick argon rich atmosphere",
               "AtmosphereType":  "ArgonRich",
               "AtmosphereComposition":  [
                                             "@{Name=Nitrogen; Percent=98.988991}",
                                             "@{Name=Argon; Percent=0.989890}"
                                         ],
               "Volcanism":  "",
               "MassEM":  0.212518,
               "Radius":  4660273.000000,
               "SurfaceGravity":  3.900154,
               "SurfaceTemperature":  117.148949,
               "SurfacePressure":  537789.875000,
               "Landable":  false,
               "Composition":  {
                                   "Ice":  0.573798,
                                   "Rock":  0.285502,
                                   "Metal":  0.140700
                               },
               "SemiMajorAxis":  757445085048.675537,
               "Eccentricity":  0.006752,
               "OrbitalInclination":  -9.494363,
               "Periapsis":  267.001438,
               "OrbitalPeriod":  713448750.972748,
               "AscendingNode":  137.005856,
               "MeanAnomaly":  7.154853,
               "RotationPeriod":  48662.553871,
               "AxialTilt":  -0.096137,
               "WasDiscovered":  false,
               "WasMapped":  false,
               "WasFootfalled":  false
           },
    "7":  {
              "timestamp":  "2026-03-15T20:55:09Z",
              "event":  "Scan",
              "ScanType":  "Detailed",
              "BodyName":  "Fachia BP-A d13 AB 3",
              "BodyID":  7,
              "Parents":  [
                              "@{Null=1}",
                              "@{Null=0}"
                          ],
              "StarSystem":  "Fachia BP-A d13",
              "SystemAddress":  459955559171,
              "DistanceFromArrivalLS":  2272.279713,
              "TidalLock":  false,
              "TerraformState":  "",
              "PlanetClass":  "High metal content body",
              "Atmosphere":  "",
              "AtmosphereType":  "None",
              "Volcanism":  "",
              "MassEM":  0.977925,
              "Radius":  6027763.500000,
              "SurfaceGravity":  10.727595,
              "SurfaceTemperature":  655.796997,
              "SurfacePressure":  0.000000,
              "Landable":  true,
              "Materials":  [
                                "@{Name=iron; Percent=22.061577}",
                                "@{Name=nickel; Percent=16.686451}",
                                "@{Name=sulphur; Percent=15.543418}",
                                "@{Name=carbon; Percent=13.070404}",
                                "@{Name=chromium; Percent=9.921824}",
                                "@{Name=manganese; Percent=9.111205}",
                                "@{Name=phosphorus; Percent=8.367898}",
                                "@{Name=arsenic; Percent=2.044172}",
                                "@{Name=molybdenum; Percent=1.440608}",
                                "@{Name=mercury; Percent=0.963393}",
                                "@{Name=technetium; Percent=0.789054}"
                            ],
              "Composition":  {
                                  "Ice":  0.000000,
                                  "Rock":  0.662593,
                                  "Metal":  0.337407
                              },
              "SemiMajorAxis":  660926443338.394165,
              "Eccentricity":  0.000045,
              "OrbitalInclination":  -0.864795,
              "Periapsis":  245.608326,
              "OrbitalPeriod":  276747572.422028,
              "AscendingNode":  -158.876969,
              "MeanAnomaly":  308.190733,
              "RotationPeriod":  60767.571523,
              "AxialTilt":  -2.579538,
              "WasDiscovered":  false,
              "WasMapped":  false,
              "WasFootfalled":  false
          },
    "2":  {
              "timestamp":  "2026-03-15T20:53:06Z",
              "event":  "Scan",
              "ScanType":  "AutoScan",
              "BodyName":  "Fachia BP-A d13 A",
              "BodyID":  2,
              "Parents":  [
                              "@{Null=1}",
                              "@{Null=0}"
                          ],
              "StarSystem":  "Fachia BP-A d13",
              "SystemAddress":  459955559171,
              "DistanceFromArrivalLS":  0.000000,
              "StarType":  "N",
              "Subclass":  0,
              "StellarMass":  0.710938,
              "Radius":  11226.562500,
              "AbsoluteMagnitude":  5.241791,
              "Age_MY":  8404,
              "SurfaceTemperature":  7866503.000000,
              "Luminosity":  "VII",
              "SemiMajorAxis":  30926175117.492676,
              "Eccentricity":  0.120425,
              "OrbitalInclination":  35.560528,
              "Periapsis":  83.705836,
              "OrbitalPeriod":  12658608.555794,
              "AscendingNode":  -96.236139,
              "MeanAnomaly":  359.186144,
              "RotationPeriod":  1.127440,
              "AxialTilt":  0.000000,
              "WasDiscovered":  false,
              "WasMapped":  false,
              "WasFootfalled":  false
          },
    "6":  {
              "Signals":  [
                              "@{Type=$SAA_SignalType_Geological;; Type_Localised=Geological; Count=3}"
                          ],
              "timestamp":  "2026-03-15T20:55:04Z",
              "event":  "Scan",
              "ScanType":  "Detailed",
              "BodyName":  "Fachia BP-A d13 AB 2",
              "BodyID":  6,
              "Parents":  [
                              "@{Null=1}",
                              "@{Null=0}"
                          ],
              "StarSystem":  "Fachia BP-A d13",
              "SystemAddress":  459955559171,
              "DistanceFromArrivalLS":  1323.630646,
              "TidalLock":  false,
              "TerraformState":  "",
              "PlanetClass":  "High metal content body",
              "Atmosphere":  "",
              "AtmosphereType":  "None",
              "Volcanism":  "minor rocky magma volcanism",
              "MassEM":  1.181682,
              "Radius":  6389886.000000,
              "SurfaceGravity":  11.535167,
              "SurfaceTemperature":  872.205017,
              "SurfacePressure":  0.000000,
              "Landable":  true,
              "Materials":  [
                                "@{Name=iron; Percent=22.340931}",
                                "@{Name=nickel; Percent=16.897743}",
                                "@{Name=sulphur; Percent=15.857106}",
                                "@{Name=carbon; Percent=13.334185}",
                                "@{Name=chromium; Percent=10.047458}",
                                "@{Name=phosphorus; Percent=8.536774}",
                                "@{Name=zinc; Percent=6.071429}",
                                "@{Name=zirconium; Percent=2.594243}",
                                "@{Name=niobium; Percent=1.526883}",
                                "@{Name=molybdenum; Percent=1.458850}",
                                "@{Name=yttrium; Percent=1.334397}"
                            ],
              "Composition":  {
                                  "Ice":  0.000000,
                                  "Rock":  0.669864,
                                  "Metal":  0.330135
                              },
              "SemiMajorAxis":  372230601310.729980,
              "Eccentricity":  0.000386,
              "OrbitalInclination":  0.011742,
              "Periapsis":  290.098006,
              "OrbitalPeriod":  116969412.565231,
              "AscendingNode":  4.254726,
              "MeanAnomaly":  140.065896,
              "RotationPeriod":  172933.811112,
              "AxialTilt":  0.244852,
              "WasDiscovered":  false,
              "WasMapped":  false,
              "WasFootfalled":  false
          },
    "31":  {
               "timestamp":  "2026-03-15T20:54:05Z",
               "event":  "Scan",
               "ScanType":  "Detailed",
               "BodyName":  "Fachia BP-A d13 C 8 a",
               "BodyID":  31,
               "Parents":  [
                               "@{Planet=30}",
                               "@{Star=4}",
                               "@{Null=0}"
                           ],
               "StarSystem":  "Fachia BP-A d13",
               "SystemAddress":  459955559171,
               "DistanceFromArrivalLS":  90787.865223,
               "TidalLock":  false,
               "TerraformState":  "",
               "PlanetClass":  "Icy body",
               "Atmosphere":  "",
               "AtmosphereType":  "None",
               "Volcanism":  "",
               "MassEM":  0.048473,
               "Radius":  3145888.250000,
               "SurfaceGravity":  1.952193,
               "SurfaceTemperature":  114.921318,
               "SurfacePressure":  0.000000,
               "Landable":  true,
               "Materials":  [
                                 "@{Name=sulphur; Percent=26.202478}",
                                 "@{Name=carbon; Percent=22.033571}",
                                 "@{Name=phosphorus; Percent=14.106271}",
                                 "@{Name=iron; Percent=12.822313}",
                                 "@{Name=nickel; Percent=9.698261}",
                                 "@{Name=chromium; Percent=5.766620}",
                                 "@{Name=manganese; Percent=5.295485}",
                                 "@{Name=zirconium; Percent=1.488935}",
                                 "@{Name=cadmium; Percent=0.995711}",
                                 "@{Name=niobium; Percent=0.876337}",
                                 "@{Name=antimony; Percent=0.714010}"
                             ],
               "Composition":  {
                                   "Ice":  0.817988,
                                   "Rock":  0.156539,
                                   "Metal":  0.025473
                               },
               "SemiMajorAxis":  2288557469.844818,
               "Eccentricity":  0.000000,
               "OrbitalInclination":  -37.293222,
               "Periapsis":  244.832499,
               "OrbitalPeriod":  39526211.619377,
               "AscendingNode":  -116.493377,
               "MeanAnomaly":  220.584751,
               "RotationPeriod":  65960.950833,
               "AxialTilt":  -0.390377,
               "WasDiscovered":  false,
               "WasMapped":  false,
               "WasFootfalled":  false
           }
}
